CHANGELOG.org
LICENSES.txt
MANIFEST.in
Makefile
README.md
circle.yml
requirements-dev.txt
requirements.txt
setup.cfg
setup.py
./pbcore/__init__.py
./pbcore/sequence.py
./pbcore/chemistry/__init__.py
./pbcore/chemistry/chemistry.py
./pbcore/chemistry/resources/mapping.xml
./pbcore/data/1.4_bas_files.fofn
./pbcore/data/2.0_bax_files.fofn
./pbcore/data/2.1_bax_files.fofn
./pbcore/data/2.1_ccs_files.fofn
./pbcore/data/2.3_bax_files.fofn
./pbcore/data/Fluidigm_human_amplicons.fasta
./pbcore/data/Fluidigm_human_amplicons.fasta.fai
./pbcore/data/Fluidigm_human_amplicons_tiny.fasta
./pbcore/data/__init__.py
./pbcore/data/aligned_reads_1.cmp.h5
./pbcore/data/barcodes-ed65-450.fasta
./pbcore/data/barcodes-ed65-450.fasta.fai
./pbcore/data/bc_files.fofn
./pbcore/data/blasr-output.m4
./pbcore/data/blasr-output.m5
./pbcore/data/empty.ccs.bam
./pbcore/data/empty.ccs.bam.pbi
./pbcore/data/lambdaNEB.fa
./pbcore/data/lambdaNEB.fa.fai
./pbcore/data/m110818_075520_42141_c100129202555500000315043109121112_s1_p0.bas.h5
./pbcore/data/m110818_075520_42141_c100129202555500000315043109121112_s2_p0.bas.h5
./pbcore/data/m130522_092457_42208_c100497142550000001823078008081323_s1_p0.1.bax.h5
./pbcore/data/m130522_092457_42208_c100497142550000001823078008081323_s1_p0.2.bax.h5
./pbcore/data/m130522_092457_42208_c100497142550000001823078008081323_s1_p0.3.bax.h5
./pbcore/data/m130522_092457_42208_c100497142550000001823078008081323_s1_p0.bas.h5
./pbcore/data/m130727_114215_42211_c100569412550000001823090301191423_s1_p0.1.ccs.h5
./pbcore/data/m130727_114215_42211_c100569412550000001823090301191423_s1_p0.ccs.bam
./pbcore/data/m130727_114215_42211_c100569412550000001823090301191423_s1_p0.ccs.bam.bai
./pbcore/data/m130727_114215_42211_c100569412550000001823090301191423_s1_p0.ccs.bam.pbi
./pbcore/data/m130731_192718_42129_c100564662550000001823085912221321_s1_p0.1.bax.h5
./pbcore/data/m130731_192718_42129_c100564662550000001823085912221321_s1_p0.1.rgn.h5
pbcore.egg-info/PKG-INFO
pbcore.egg-info/SOURCES.txt
pbcore.egg-info/dependency_links.txt
pbcore.egg-info/entry_points.txt
pbcore.egg-info/not-zip-safe
pbcore.egg-info/requires.txt
pbcore.egg-info/top_level.txt
