Metadata-Version: 1.0
Name: pbcore
Version: 1.2.10
Summary: A Python library for reading and writing PacBio® data files
Home-page: UNKNOWN
Author: Pacific Biosciences
Author-email: devnet@pacificbiosciences.com
License: PacBio "BSD clear" license:
